ParsAdvent/Funciones.py
ParsAdvent/__init__.py
ParsAdvent-1.0.dist-info/METADATA
ParsAdvent-1.0.dist-info/WHEEL
ParsAdvent-1.0.dist-info/top_level.txt
ParsAdvent-1.0.dist-info/RECORD
