Metadata-Version: 2.1
Name: ParsAdvent
Version: 1.0
Summary: Librería para crear aventuras conversacionales.
Home-page: UNKNOWN
Author: Dionisio David Peñalosa Mauri
Author-email: dionisiopenalosa@iesjulioverne.es
License: GPL
Platform: UNKNOWN
